dup_fmt/__about__.py
dup_fmt/__init__.py
dup_fmt/__main__.py
dup_fmt/cli.py
dup_fmt/exceptions.py
dup_fmt/formatter.py
dup_fmt/utils.py
dup_fmt-0.1.4.dist-info/METADATA
dup_fmt-0.1.4.dist-info/WHEEL
dup_fmt-0.1.4.dist-info/entry_points.txt
dup_fmt-0.1.4.dist-info/licenses/LICENSE
dup_fmt-0.1.4.dist-info/RECORD
