Metadata-Version: 2.1
Name: dup-fmt
Version: 0.1.4
Summary: The utility formatter objects for the data engine package
Project-URL: Homepage, https://github.com/korawica/dup-fmt/
Project-URL: Source Code, https://github.com/korawica/dup-fmt/
Author-email: korawica <korawich.anu@gmail.com>
License-Expression: MIT
License-File: LICENSE
Keywords: data,formatter
Classifier: Development Status :: 4 - Beta
Classifier: Natural Language :: English
Classifier: Operating System :: OS Independent
Classifier: Programming Language :: Python
Classifier: Programming Language :: Python :: 3 :: Only
Classifier: Programming Language :: Python :: 3.8
Classifier: Programming Language :: Python :: 3.9
Classifier: Programming Language :: Python :: 3.10
Classifier: Programming Language :: Python :: 3.11
Classifier: Topic :: Utilities
Requires-Python: >=3.8.10
Requires-Dist: dup-utils>=0.0.5.post0
Requires-Dist: packaging<24,>=23.1
Requires-Dist: python-dateutil<3.0.0,>=2.8.2
Provides-Extra: dev
Requires-Dist: dup-fmt[test]; extra == 'dev'
Requires-Dist: hatch>=1.6.0; extra == 'dev'
Provides-Extra: test
Requires-Dist: dup-utils[test]>=0.0.5.post0; extra == 'test'
